src/cla_n.v
// file: cla_n.v
// author: @refaay

`timescale 1ns/1ns

module cla_n(a, b, ci, s, co);
parameter n = 4; // Default
input [n-1:0] a, b;
input ci;
output [n-1:0] s;
output co;
wire [n-1:0] g;
wire [n-1:0] p;
wire [n:0] c;
assign c[0] = ci;
assign co = c[n];
genvar i; /* i - generate index variable */
generate
for (i=0; i<n; i=i+1) begin: addbit
assign s[i] = a[i] ^ b[i] ^ c[i];
assign g[i] = a[i] & b[i];
assign p[i] = a[i] | b[i];
assign c[i+1] = g[i] | (p[i] & c[i]);
end
endgenerate
endmodule

src/cla_n_tb.v
// file: cla_n_tb.v
// author: @refaay
// Testbench for cla_n

`timescale 1ns/1ns

module cla_n_tb;

	//Inputs
	reg [3: 0] a;
	reg [3: 0] b;
	reg ci;


	//Outputs
	wire [3: 0] s, ref_s;
	wire co, ref_co;
	wire err;


	//Instantiation of Unit Under Test
	cla_n uut (
		.a(a),
		.b(b),
		.ci(ci),
		.s(s),
		.co(co)
	);


	
	// Golden Model
    assign {ref_co, ref_s} = a + b + ci;
    
    // Checker
    assign err = (ref_s != s) || (ref_co != co);


	// Stimulu Generator
    integer A_i, B_i;
    initial begin
    ci = 0;
    for(A_i=0; A_i<16; A_i=A_i+1)
    for(B_i=0; B_i<16; B_i=B_i+1) begin
    #5 b = B_i;
    a = A_i;
    end
    #10;
    ci = 1;
    for(A_i=0; A_i<16; A_i=A_i+1)
    for(B_i=0; B_i<16; B_i=B_i+1) begin
    #5 b = B_i;
    a = A_i;
    end
    end


endmodule

build (read-only)/cla_n_tb.vcd
$date
	Mon Nov 14 17:36:45 2016
$end
$version
	Icarus Verilog
$end
$timescale
	1ns
$end
$scope module cla_n_tb $end
$var wire 1 ! err $end
$var wire 4 " s [3:0] $end
$var wire 4 # ref_s [3:0] $end
$var wire 1 $ ref_co $end
$var wire 1 % co $end
$var reg 4 & a [3:0] $end
$var reg 4 ' b [3:0] $end
$var reg 1 ( ci $end
$var integer 32 ) A_i [31:0] $end
$var integer 32 * B_i [31:0] $end
$scope module uut $end
$var wire 4 + a [3:0] $end
$var wire 4 , b [3:0] $end
$var wire 1 ( ci $end
$var wire 4 - s [3:0] $end
$var wire 4 . p [3:0] $end
$var wire 4 / g [3:0] $end
$var wire 1 % co $end
$var wire 5 0 c [4:0] $end
$scope begin addbit[0] $end
$upscope $end
$scope begin addbit[1] $end
$upscope $end
$scope begin addbit[2] $end
$upscope $end
$scope begin addbit[3] $end
$upscope $end
$upscope $end
$upscope $end
$enddefinitions $end
#0
$dumpvars
bx0 0
bx /
bx .
bx -
bx ,
bx +
b0 *
b0 )
0(
bx '
bx &
x%
x$
bx #
bx "
x!
$end
#5
0!
0%
b0 0
b0 "
b0 -
b0 /
b0 .
b0 #
0$
b1 *
b0 &
b0 +
b0 '
b0 ,
#10
b1 "
b1 -
0!
b1 .
b1 #
b10 *
b1 '
b1 ,
#15
b10 "
b10 -
0!
b10 .
b10 #
b11 *
b10 '
b10 ,
#20
b11 "
b11 -
0!
b11 .
b11 #
b100 *
b11 '
b11 ,
#25
b100 "
b100 -
0!
b100 .
b100 #
b101 *
b100 '
b100 ,
#30
b101 "
b101 -
0!
b101 .
b101 #
b110 *
b101 '
b101 ,
#35
b110 "
b110 -
0!
b110 .
b110 #
b111 *
b110 '
b110 ,
#40
b111 "
b111 -
0!
b111 .
b111 #
b1000 *
b111 '
b111 ,
#45
b1000 "
b1000 -
0!
b1000 .
b1000 #
b1001 *
b1000 '
b1000 ,
#50
b1001 "
b1001 -
0!
b1001 .
b1001 #
b1010 *
b1001 '
b1001 ,
#55
b1010 "
b1010 -
0!
b1010 .
b1010 #
b1011 *
b1010 '
b1010 ,
#60
b1011 "
b1011 -
0!
b1011 .
b1011 #
b1100 *
b1011 '
b1011 ,
#65
b1100 "
b1100 -
0!
b1100 .
b1100 #
b1101 *
b1100 '
b1100 ,
#70
b1101 "
b1101 -
0!
b1101 .
b1101 #
b1110 *
b1101 '
b1101 ,
#75
b1110 "
b1110 -
0!
b1110 .
b1110 #
b1111 *
b1110 '
b1110 ,
#80
b1111 "
b1111 -
0!
b1111 .
b1111 #
b1 )
b0 *
b1111 '
b1111 ,
#85
b1 "
b1 -
0!
b1 .
b1 #
b1 *
b1 &
b1 +
b0 '
b0 ,
#90
b10 0
b10 "
b10 -
0!
b1 /
b10 #
b10 *
b1 '
b1 ,
#95
b0 0
b11 "
b11 -
0!
b0 /
b11 .
b11 #
b11 *
b10 '
b10 ,
#100
b110 0
b100 "
b100 -
0!
b1 /
b100 #
b100 *
b11 '
b11 ,
#105
b0 0
b101 "
b101 -
0!
b0 /
b101 .
b101 #
b101 *
b100 '
b100 ,
#110
b10 0
b110 "
b110 -
0!
b1 /
b110 #
b110 *
b101 '
b101 ,
#115
b0 0
b111 "
b111 -
0!
b0 /
b111 .
b111 #
b111 *
b110 '
b110 ,
#120
b1110 0
b1000 "
b1000 -
0!
b1 /
b1000 #
b1000 *
b111 '
b111 ,
#125
0%
b0 0
b1001 "
b1001 -
0!
b0 /
b1001 .
b1001 #
b1001 *
b1000 '
b1000 ,
#130
b10 0
b1010 "
b1010 -
0!
b1 /
b1010 #
b1010 *
b1001 '
b1001 ,
#135
b0 0
b1011 "
b1011 -
0!
b0 /
b1011 .
b1011 #
b1011 *
b1010 '
b1010 ,
#140
b110 0
b1100 "
b1100 -
0!
b1 /
b1100 #
b1100 *
b1011 '
b1011 ,
#145
0%
b0 0
b1101 "
b1101 -
0!
b0 /
b1101 .
b1101 #
b1101 *
b1100 '
b1100 ,
#150
b10 0
b1110 "
b1110 -
0!
b1 /
b1110 #
b1110 *
b1101 '
b1101 ,
#155
0%
b0 0
b1111 "
b1111 -
0!
b0 /
b1111 .
b1111 #
b1111 *
b1110 '
b1110 ,
#160
1%
b11110 0
b0 "
b0 -
0!
b1 /
b0 #
1$
b10 )
b0 *
b1111 '
b1111 ,
#165
0%
b0 0
b10 "
b10 -
0!
b0 /
b10 .
b10 #
0$
b1 *
b10 &
b10 +
b0 '
b0 ,
#170
b11 "
b11 -
0!
b11 .
b11 #
b10 *
b1 '
b1 ,
#175
b100 0
b100 "
b100 -
0!
b10 .
b10 /
b100 #
b11 *
b10 '
b10 ,
#180
b101 "
b101 -
0!
b11 .
b101 #
b100 *
b11 '
b11 ,
#185
b0 0
b110 "
b110 -
0!
b0 /
b110 .
b110 #
b101 *
b100 '
b100 ,
#190
b111 "
b111 -
0!
b111 .
b111 #
b110 *
b101 '
b101 ,
#195
b1100 0
b1000 "
b1000 -
0!
b110 .
b10 /
b1000 #
b111 *
b110 '
b110 ,
#200
b1001 "
b1001 -
0!
b111 .
b1001 #
b1000 *
b111 '
b111 ,
#205
0%
b0 0
b1010 "
b1010 -
0!
b0 /
b1010 .
b1010 #
b1001 *
b1000 '
b1000 ,
#210
b1011 "
b1011 -
0!
b1011 .
b1011 #
b1010 *
b1001 '
b1001 ,
#215
b100 0
b1100 "
b1100 -
0!
b1010 .
b10 /
b1100 #
b1011 *
b1010 '
b1010 ,
#220
b1101 "
b1101 -
0!
b1011 .
b1101 #
b1100 *
b1011 '
b1011 ,
#225
0%
b0 0
b1110 "
b1110 -
0!
b0 /
b1110 .
b1110 #
b1101 *
b1100 '
b1100 ,
#230
b1111 "
b1111 -
0!
b1111 .
b1111 #
b1110 *
b1101 '
b1101 ,
#235
1%
b11100 0
b0 "
b0 -
0!
b1110 .
b10 /
b0 #
1$
b1111 *
b1110 '
b1110 ,
#240
b1 "
b1 -
0!
b1111 .
b1 #
b11 )
b0 *
b1111 '
b1111 ,
#245
0%
b0 0
b11 "
b11 -
0!
b0 /
b11 .
b11 #
0$
b1 *
b11 &
b11 +
b0 '
b0 ,
#250
b110 0
b100 "
b100 -
0!
b1 /
b100 #
b10 *
b1 '
b1 ,
#255
b100 0
b101 "
b101 -
0!
b10 /
b101 #
b11 *
b10 '
b10 ,
#260
b110 0
b110 "
b110 -
0!
b11 /
b110 #
b100 *
b11 '
b11 ,
#265
b0 0
b111 "
b111 -
0!
b0 /
b111 .
b111 #
b101 *
b100 '
b100 ,
#270
b1110 0
b1000 "
b1000 -
0!
b1 /
b1000 #
b110 *
b101 '
b101 ,
#275
b1100 0
b1001 "
b1001 -
0!
b10 /
b1001 #
b111 *
b110 '
b110 ,
#280
b1110 0
b1010 "
b1010 -
0!
b11 /
b1010 #
b1000 *
b111 '
b111 ,
#285
0%
b0 0
b1011 "
b1011 -
0!
b0 /
b1011 .
b1011 #
b1001 *
b1000 '
b1000 ,
#290
b110 0
b1100 "
b1100 -
0!
b1 /
b1100 #
b1010 *
b1001 '
b1001 ,
#295
b100 0
b1101 "
b1101 -
0!
b10 /
b1101 #
b1011 *
b1010 '
b1010 ,
#300
b110 0
b1110 "
b1110 -
0!
b11 /
b1110 #
b1100 *
b1011 '
b1011 ,
#305
0%
b0 0
b1111 "
b1111 -
0!
b0 /
b1111 .
b1111 #
b1101 *
b1100 '
b1100 ,
#310
1%
b11110 0
b0 "
b0 -
0!
b1 /
b0 #
1$
b1110 *
b1101 '
b1101 ,
#315
b11100 0
b1 "
b1 -
0!
b10 /
b1 #
b1111 *
b1110 '
b1110 ,
#320
b11110 0
b10 "
b10 -
0!
b11 /
b10 #
b100 )
b0 *
b1111 '
b1111 ,
#325
0%
b0 0
b100 "
b100 -
0!
b0 /
b100 .
b100 #
0$
b1 *
b100 &
b100 +
b0 '
b0 ,
#330
b101 "
b101 -
0!
b101 .
b101 #
b10 *
b1 '
b1 ,
#335
b110 "
b110 -
0!
b110 .
b110 #
b11 *
b10 '
b10 ,
#340
b111 "
b111 -
0!
b111 .
b111 #
b100 *
b11 '
b11 ,
#345
b1000 0
b1000 "
b1000 -
0!
b100 .
b100 /
b1000 #
b101 *
b100 '
b100 ,
#350
b1001 "
b1001 -
0!
b101 .
b1001 #
b110 *
b101 '
b101 ,
#355
b1010 "
b1010 -
0!
b110 .
b1010 #
b111 *
b110 '
b110 ,
#360
b1011 "
b1011 -
0!
b111 .
b1011 #
b1000 *
b111 '
b111 ,
#365
0%
b0 0
b1100 "
b1100 -
0!
b0 /
b1100 .
b1100 #
b1001 *
b1000 '
b1000 ,
#370
b1101 "
b1101 -
0!
b1101 .
b1101 #
b1010 *
b1001 '
b1001 ,
#375
b1110 "
b1110 -
0!
b1110 .
b1110 #
b1011 *
b1010 '
b1010 ,
#380
b1111 "
b1111 -
0!
b1111 .
b1111 #
b1100 *
b1011 '
b1011 ,
#385
1%
b11000 0
b0 "
b0 -
0!
b1100 .
b100 /
b0 #
1$
b1101 *
b1100 '
b1100 ,
#390
b1 "
b1 -
0!
b1101 .
b1 #
b1110 *
b1101 '
b1101 ,
#395
b10 "
b10 -
0!
b1110 .
b10 #
b1111 *
b1110 '
b1110 ,
#400
b11 "
b11 -
0!
b1111 .
b11 #
b101 )
b0 *
b1111 '
b1111 ,
#405
0%
b0 0
b101 "
b101 -
0!
b0 /
b101 .
b101 #
0$
b1 *
b101 &
b101 +
b0 '
b0 ,
#410
b10 0
b110 "
b110 -
0!
b1 /
b110 #
b10 *
b1 '
b1 ,
#415
b0 0
b111 "
b111 -
0!
b0 /
b111 .
b111 #
b11 *
b10 '
b10 ,
#420
b1110 0
b1000 "
b1000 -
0!
b1 /
b1000 #
b100 *
b11 '
b11 ,
#425
b1000 0
b1001 "
b1001 -
0!
b101 .
b100 /
b1001 #
b101 *
b100 '
b100 ,
#430
b1010 0
b1010 "
b1010 -
0!
b101 /
b1010 #
b110 *
b101 '
b101 ,
#435
b1000 0
b1011 "
b1011 -
0!
b100 /
b111 .
b1011 #
b111 *
b110 '
b110 ,
#440
b1110 0
b1100 "
b1100 -
0!
b101 /
b1100 #
b1000 *
b111 '
b111 ,
#445
0%
b0 0
b1101 "
b1101 -
0!
b0 /
b1101 .
b1101 #
b1001 *
b1000 '
b1000 ,
#450
b10 0
b1110 "
b1110 -
0!
b1 /
b1110 #
b1010 *
b1001 '
b1001 ,
#455
0%
b0 0
b1111 "
b1111 -
0!
b0 /
b1111 .
b1111 #
b1011 *
b1010 '
b1010 ,
#460
1%
b11110 0
b0 "
b0 -
0!
b1 /
b0 #
1$
b1100 *
b1011 '
b1011 ,
#465
b11000 0
b1 "
b1 -
0!
b1101 .
b100 /
b1 #
b1101 *
b1100 '
b1100 ,
#470
b11010 0
b10 "
b10 -
0!
b101 /
b10 #
b1110 *
b1101 '
b1101 ,
#475
b11000 0
b11 "
b11 -
0!
b100 /
b1111 .
b11 #
b1111 *
b1110 '
b1110 ,
#480
b11110 0
b100 "
b100 -
0!
b101 /
b100 #
b110 )
b0 *
b1111 '
b1111 ,
#485
0%
b0 0
b110 "
b110 -
0!
b0 /
b110 .
b110 #
0$
b1 *
b110 &
b110 +
b0 '
b0 ,
#490
b111 "
b111 -
0!
b111 .
b111 #
b10 *
b1 '
b1 ,
#495
b1100 0
b1000 "
b1000 -
0!
b110 .
b10 /
b1000 #
b11 *
b10 '
b10 ,
#500
b1001 "
b1001 -
0!
b111 .
b1001 #
b100 *
b11 '
b11 ,
#505
b1000 0
b1010 "
b1010 -
0!
b110 .
b100 /
b1010 #
b101 *
b100 '
b100 ,
#510
b1011 "
b1011 -
0!
b111 .
b1011 #
b110 *
b101 '
b101 ,
#515
b1100 0
b1100 "
b1100 -
0!
b110 .
b110 /
b1100 #
b111 *
b110 '
b110 ,
#520
b1101 "
b1101 -
0!
b111 .
b1101 #
b1000 *
b111 '
b111 ,
#525
0%
b0 0
b1110 "
b1110 -
0!
b0 /
b1110 .
b1110 #
b1001 *
b1000 '
b1000 ,
#530
b1111 "
b1111 -
0!
b1111 .
b1111 #
b1010 *
b1001 '
b1001 ,
#535
1%
b11100 0
b0 "
b0 -
0!
b1110 .
b10 /
b0 #
1$
b1011 *
b1010 '
b1010 ,
#540
b1 "
b1 -
0!
b1111 .
b1 #
b1100 *
b1011 '
b1011 ,
#545
b11000 0
b10 "
b10 -
0!
b1110 .
b100 /
b10 #
b1101 *
b1100 '
b1100 ,
#550
b11 "
b11 -
0!
b1111 .
b11 #
b1110 *
b1101 '
b1101 ,
#555
b11100 0
b100 "
b100 -
0!
b1110 .
b110 /
b100 #
b1111 *
b1110 '
b1110 ,
#560
b101 "
b101 -
0!
b1111 .
b101 #
b111 )
b0 *
b1111 '
b1111 ,
#565
0%
b0 0
b111 "
b111 -
0!
b0 /
b111 .
b111 #
0$
b1 *
b111 &
b111 +
b0 '
b0 ,
#570
b1110 0
b1000 "
b1000 -
0!
b1 /
b1000 #
b10 *
b1 '
b1 ,
#575
b1100 0
b1001 "
b1001 -
0!
b10 /
b1001 #
b11 *
b10 '
b10 ,
#580
b1110 0
b1010 "
b1010 -
0!
b11 /
b1010 #
b100 *
b11 '
b11 ,
#585
b1000 0
b1011 "
b1011 -
0!
b100 /
b1011 #
b101 *
b100 '
b100 ,
#590
b1110 0
b1100 "
b1100 -
0!
b101 /
b1100 #
b110 *
b101 '
b101 ,
#595
b1100 0
b1101 "
b1101 -
0!
b110 /
b1101 #
b111 *
b110 '
b110 ,
#600
b1110 0
b1110 "
b1110 -
0!
b111 /
b1110 #
b1000 *
b111 '
b111 ,
#605
0%
b0 0
b1111 "
b1111 -
0!
b0 /
b1111 .
b1111 #
b1001 *
b1000 '
b1000 ,
#610
1%
b11110 0
b0 "
b0 -
0!
b1 /
b0 #
1$
b1010 *
b1001 '
b1001 ,
#615
b11100 0
b1 "
b1 -
0!
b10 /
b1 #
b1011 *
b1010 '
b1010 ,
#620
b11110 0
b10 "
b10 -
0!
b11 /
b10 #
b1100 *
b1011 '
b1011 ,
#625
b11000 0
b11 "
b11 -
0!
b100 /
b11 #
b1101 *
b1100 '
b1100 ,
#630
b11110 0
b100 "
b100 -
0!
b101 /
b100 #
b1110 *
b1101 '
b1101 ,
#635
b11100 0
b101 "
b101 -
0!
b110 /
b101 #
b1111 *
b1110 '
b1110 ,
#640
b11110 0
b110 "
b110 -
0!
b111 /
b110 #
b1000 )
b0 *
b1111 '
b1111 ,
#645
0%
b1000 "
b1000 -
b0 0
0!
b0 /
b1000 .
b1000 #
0$
b1 *
b1000 &
b1000 +
b0 '
b0 ,
#650
b1001 "
b1001 -
0!
b1001 .
b1001 #
b10 *
b1 '
b1 ,
#655
b1010 "
b1010 -
0!
b1010 .
b1010 #
b11 *
b10 '
b10 ,
#660
b1011 "
b1011 -
0!
b1011 .
b1011 #
b100 *
b11 '
b11 ,
#665
b1100 "
b1100 -
0!
b1100 .
b1100 #
b101 *
b100 '
b100 ,
#670
b1101 "
b1101 -
0!
b1101 .
b1101 #
b110 *
b101 '
b101 ,
#675
b1110 "
b1110 -
0!
b1110 .
b1110 #
b111 *
b110 '
b110 ,
#680
b1111 "
b1111 -
0!
b1111 .
b1111 #
b1000 *
b111 '
b111 ,
#685
1%
b10000 0
b0 "
b0 -
0!
b1000 .
b1000 /
b0 #
1$
b1001 *
b1000 '
b1000 ,
#690
b1 "
b1 -
0!
b1001 .
b1 #
b1010 *
b1001 '
b1001 ,
#695
b10 "
b10 -
0!
b1010 .
b10 #
b1011 *
b1010 '
b1010 ,
#700
b11 "
b11 -
0!
b1011 .
b11 #
b1100 *
b1011 '
b1011 ,
#705
b100 "
b100 -
0!
b1100 .
b100 #
b1101 *
b1100 '
b1100 ,
#710
b101 "
b101 -
0!
b1101 .
b101 #
b1110 *
b1101 '
b1101 ,
#715
b110 "
b110 -
0!
b1110 .
b110 #
b1111 *
b1110 '
b1110 ,
#720
b111 "
b111 -
0!
b1111 .
b111 #
b1001 )
b0 *
b1111 '
b1111 ,
#725
0%
b0 0
b1001 "
b1001 -
0!
b1001 .
b0 /
b1001 #
0$
b1 *
b1001 &
b1001 +
b0 '
b0 ,
#730
b10 0
b1010 "
b1010 -
0!
b1 /
b1010 #
b10 *
b1 '
b1 ,
#735
b0 0
b1011 "
b1011 -
0!
b0 /
b1011 .
b1011 #
b11 *
b10 '
b10 ,
#740
b110 0
b1100 "
b1100 -
0!
b1 /
b1100 #
b100 *
b11 '
b11 ,
#745
0%
b0 0
b1101 "
b1101 -
0!
b0 /
b1101 .
b1101 #
b101 *
b100 '
b100 ,
#750
b10 0
b1110 "
b1110 -
0!
b1 /
b1110 #
b110 *
b101 '
b101 ,
#755
0%
b0 0
b1111 "
b1111 -
0!
b0 /
b1111 .
b1111 #
b111 *
b110 '
b110 ,
#760
1%
b11110 0
b0 "
b0 -
0!
b1 /
b0 #
1$
b1000 *
b111 '
b111 ,
#765
b10000 0
b1 "
b1 -
0!
b1001 .
b1000 /
b1 #
b1001 *
b1000 '
b1000 ,
#770
b10010 0
b10 "
b10 -
0!
b1001 /
b10 #
b1010 *
b1001 '
b1001 ,
#775
b10000 0
b11 "
b11 -
0!
b1000 /
b1011 .
b11 #
b1011 *
b1010 '
b1010 ,
#780
b10110 0
b100 "
b100 -
0!
b1001 /
b100 #
b1100 *
b1011 '
b1011 ,
#785
b10000 0
b101 "
b101 -
0!
b1000 /
b1101 .
b101 #
b1101 *
b1100 '
b1100 ,
#790
b10010 0
b110 "
b110 -
0!
b1001 /
b110 #
b1110 *
b1101 '
b1101 ,
#795
b10000 0
b111 "
b111 -
0!
b1000 /
b1111 .
b111 #
b1111 *
b1110 '
b1110 ,
#800
b11110 0
b1000 "
b1000 -
0!
b1001 /
b1000 #
b1010 )
b0 *
b1111 '
b1111 ,
#805
0%
b0 0
b1010 "
b1010 -
0!
b1010 .
b0 /
b1010 #
0$
b1 *
b1010 &
b1010 +
b0 '
b0 ,
#810
b1011 "
b1011 -
0!
b1011 .
b1011 #
b10 *
b1 '
b1 ,
#815
b100 0
b1100 "
b1100 -
0!
b1010 .
b10 /
b1100 #
b11 *
b10 '
b10 ,
#820
b1101 "
b1101 -
0!
b1011 .
b1101 #
b100 *
b11 '
b11 ,
#825
0%
b0 0
b1110 "
b1110 -
0!
b0 /
b1110 .
b1110 #
b101 *
b100 '
b100 ,
#830
b1111 "
b1111 -
0!
b1111 .
b1111 #
b110 *
b101 '
b101 ,
#835
1%
b11100 0
b0 "
b0 -
0!
b1110 .
b10 /
b0 #
1$
b111 *
b110 '
b110 ,
#840
b1 "
b1 -
0!
b1111 .
b1 #
b1000 *
b111 '
b111 ,
#845
b10000 0
b10 "
b10 -
0!
b1010 .
b1000 /
b10 #
b1001 *
b1000 '
b1000 ,
#850
b11 "
b11 -
0!
b1011 .
b11 #
b1010 *
b1001 '
b1001 ,
#855
b10100 0
b100 "
b100 -
0!
b1010 .
b1010 /
b100 #
b1011 *
b1010 '
b1010 ,
#860
b101 "
b101 -
0!
b1011 .
b101 #
b1100 *
b1011 '
b1011 ,
#865
b10000 0
b110 "
b110 -
0!
b1000 /
b1110 .
b110 #
b1101 *
b1100 '
b1100 ,
#870
b111 "
b111 -
0!
b1111 .
b111 #
b1110 *
b1101 '
b1101 ,
#875
b11100 0
b1000 "
b1000 -
0!
b1110 .
b1010 /
b1000 #
b1111 *
b1110 '
b1110 ,
#880
b1001 "
b1001 -
0!
b1111 .
b1001 #
b1011 )
b0 *
b1111 '
b1111 ,
#885
0%
b0 0
b1011 "
b1011 -
0!
b1011 .
b0 /
b1011 #
0$
b1 *
b1011 &
b1011 +
b0 '
b0 ,
#890
b110 0
b1100 "
b1100 -
0!
b1 /
b1100 #
b10 *
b1 '
b1 ,
#895
b100 0
b1101 "
b1101 -
0!
b10 /
b1101 #
b11 *
b10 '
b10 ,
#900
b110 0
b1110 "
b1110 -
0!
b11 /
b1110 #
b100 *
b11 '
b11 ,
#905
0%
b0 0
b1111 "
b1111 -
0!
b0 /
b1111 .
b1111 #
b101 *
b100 '
b100 ,
#910
1%
b11110 0
b0 "
b0 -
0!
b1 /
b0 #
1$
b110 *
b101 '
b101 ,
#915
b11100 0
b1 "
b1 -
0!
b10 /
b1 #
b111 *
b110 '
b110 ,
#920
b11110 0
b10 "
b10 -
0!
b11 /
b10 #
b1000 *
b111 '
b111 ,
#925
b10000 0
b11 "
b11 -
0!
b1011 .
b1000 /
b11 #
b1001 *
b1000 '
b1000 ,
#930
b10110 0
b100 "
b100 -
0!
b1001 /
b100 #
b1010 *
b1001 '
b1001 ,
#935
b10100 0
b101 "
b101 -
0!
b1010 /
b101 #
b1011 *
b1010 '
b1010 ,
#940
b10110 0
b110 "
b110 -
0!
b1011 /
b110 #
b1100 *
b1011 '
b1011 ,
#945
b10000 0
b111 "
b111 -
0!
b1000 /
b1111 .
b111 #
b1101 *
b1100 '
b1100 ,
#950
b11110 0
b1000 "
b1000 -
0!
b1001 /
b1000 #
b1110 *
b1101 '
b1101 ,
#955
b11100 0
b1001 "
b1001 -
0!
b1010 /
b1001 #
b1111 *
b1110 '
b1110 ,
#960
b11110 0
b1010 "
b1010 -
0!
b1011 /
b1010 #
b1100 )
b0 *
b1111 '
b1111 ,
#965
0%
b0 0
b1100 "
b1100 -
0!
b1100 .
b0 /
b1100 #
0$
b1 *
b1100 &
b1100 +
b0 '
b0 ,
#970
b1101 "
b1101 -
0!
b1101 .
b1101 #
b10 *
b1 '
b1 ,
#975
b1110 "
b1110 -
0!
b1110 .
b1110 #
b11 *
b10 '
b10 ,
#980
b1111 "
b1111 -
0!
b1111 .
b1111 #
b100 *
b11 '
b11 ,
#985
1%
b11000 0
b0 "
b0 -
0!
b1100 .
b100 /
b0 #
1$
b101 *
b100 '
b100 ,
#990
b1 "
b1 -
0!
b1101 .
b1 #
b110 *
b101 '
b101 ,
#995
b10 "
b10 -
0!
b1110 .
b10 #
b111 *
b110 '
b110 ,
#1000
b11 "
b11 -
0!
b1111 .
b11 #
b1000 *
b111 '
b111 ,
