src/cla_n.v
// file: cla_n.v
// author: @refaay

`timescale 1ns/1ns

module cla_n(a, b, ci, s, co);
parameter n = 4; // Default
input [n-1:0] a, b;
input ci;
output [n-1:0] s;
output co;
wire [n-1:0] g;
wire [n-1:0] p;
wire [n:0] c;
assign c[0] = ci;
assign co = c[n];
genvar i; /* i - generate index variable */
generate
for (i=0; i<n; i=i+1) begin: addbit
assign s[i] = a[i] ^ b[i] ^ c[i];
assign g[i] = a[i] & b[i];
assign p[i] = a[i] | b[i];
assign c[i+1] = g[i] | (p[i] & c[i]);
end
endgenerate
endmodule

src/mux_2x1_n.v
// file: mux_2x1_n.v
// author: @refaay

`timescale 1ns/1ns

module mux_2x1_n(a, b, sel, out);
parameter n = 1;
input [n-1:0] a, b;
input sel;
output [n-1:0] out;
genvar i;
generate
for (i=0; i<n; i=i+1) begin: addbit
assign out[i] = ~sel & a[i] | sel & b[i];

end
endgenerate

endmodule

src/FA.v
// file: FA.v
// author: @refaay

`timescale 1ns/1ns

module FA(input A, input B, input cin, output S, output cout);
wire w1, w2, w3, w4;
xor xor1 (w1, A, B);
xor xor2 (S, w1, cin);
and and1 (w2, A, B);
and and2 (w3, A, cin);
and and3 (w4, B, cin);
or or1 (cout, w2, w3, w4);
endmodule

src/rca_n.v
// file: rca_n.v
// author: @refaay

`timescale 1ns/1ns

module rca_n(a, b, ci, s, co);
parameter n = 32; // Default
input [n-1:0] a, b;
input ci;
output [n-1:0] s;
output co;
wire [n:0] c;
assign c[0] = ci;
assign co = c[n];
genvar i;
generate
for (i=0; i<n; i=i+1) begin: addbit
FA f (a[i], b[i], c[i], s[i], c[i+1]); // FA fa (.A(a[i]), .B(b[i], .cin(c[i]), .S(s[i]), .cout(c[i+1]));
end
endgenerate
endmodule

src/csa_n.v
// file: csa_n.v
// author: @refaay

`timescale 1ns/1ns

module csa_n(a, b, ci, s, co);
parameter n = 16; // Default
parameter k = 8;
parameter blockType = 0; // 0 if RCA, 1 if CLA
input [n-1:0] a, b;
input ci;
output [n-1:0] s;
output co;
wire c[n/k-1:0];
assign co = c[n/k-1];
wire [n-1:k]s_0;
wire [n-1:k]s_1;
wire [n/k-1:1] c_0;
wire [n/k-1:1] c_1;

genvar i; 
generate
if (blockType == 0) begin: addbit // RCA
rca_n #(k) rca_initial (a[k-1:0], b[k-1:0], ci, s[k-1:0], c[0]);
for (i=k; i<n; i=i+k) begin
rca_n #(k) rca_0 (a[i+k-1:i], b[i+k-1:i], 1'b0, s_0[i+k-1:i], c_0[i/k]); // Default
rca_n #(k) rca_1 (a[i+k-1:i], b[i+k-1:i], 1'b1, s_1[i+k-1:i], c_1[i/k]);
mux_2x1_n #(k+1) muxes ({c_0[i/k], s_0[i+k-1:i]}, {c_1[i/k], s_1[i+k-1:i]}, c[i/k-1], {c[i/k], s[i+k-1:i]});
end
end


else begin: addbit // CLA

cla_n #(k) cla_initial (a[k-1:0], b[k-1:0], ci, s[k-1:0], c[0]);
for (i=k; i<n; i=i+k) begin
cla_n #(k) cla_0 (a[i+k-1:i], b[i+k-1:i], 1'b0, s_0[i+k-1:i], c_0[i/k]); // Default
cla_n #(k) cla_1 (a[i+k-1:i], b[i+k-1:i], 1'b1, s_1[i+k-1:i], c_1[i/k]);
mux_2x1_n #(k+1) muxes ({c_0[i/k], s_0[i+k-1:i]}, {c_1[i/k], s_1[i+k-1:i]}, c[i/k-1], {c[i/k], s[i+k-1:i]});
end
end

endgenerate
endmodule

src/csa_n_tb.v
// file: csa_n_tb.v
// author: @refaay
// Testbench for csa_n

`timescale 1ns/1ns

module csa_n_tb;

	//Inputs
	reg [3: 0] a;
	reg [3: 0] b;
	reg ci;

//Outputs
	wire [3: 0] s, ref_s;
	wire co, ref_co;
	wire err;
	
	//Instantiation of Unit Under Test
	csa_n uut (
		.a(a),
		.b(b),
		.ci(ci),
		.s(s),
		.co(co)
	);

	
	// Golden Model
    assign {ref_co, ref_s} = a + b + ci;
    
    // Checker
    assign err = (ref_s != s) || (ref_co != co);


	// Stimulu Generator
    integer A_i, B_i;
    initial begin
    ci = 0;
    for(A_i=0; A_i<16; A_i=A_i+1)
    for(B_i=0; B_i<16; B_i=B_i+1) begin
    #5 b = B_i;
    a = A_i;
    end
    #10;
    ci = 1;
    for(A_i=0; A_i<16; A_i=A_i+1)
    for(B_i=0; B_i<16; B_i=B_i+1) begin
    #5 b = B_i;
    a = A_i;
    end
    end


endmodule

build (read-only)/csa_n_tb.vcd
$date
	Tue Nov 15 14:34:28 2016
$end
$version
	Icarus Verilog
$end
$timescale
	1ns
$end
$scope module csa_n_tb $end
$var wire 1 ! err $end
$var wire 4 " s [3:0] $end
$var wire 4 # ref_s [3:0] $end
$var wire 1 $ ref_co $end
$var wire 1 % co $end
$var reg 4 & a [3:0] $end
$var reg 4 ' b [3:0] $end
$var reg 1 ( ci $end
$var integer 32 ) A_i [31:0] $end
$var integer 32 * B_i [31:0] $end
$scope module uut $end
$var wire 4 + a [3:0] $end
$var wire 4 , b [3:0] $end
$var wire 1 ( ci $end
$var wire 1 % co $end
$var wire 2 - s_1 [3:2] $end
$var wire 2 . s_0 [3:2] $end
$var wire 4 / s [3:0] $end
$var wire 1 0 c_1 [1:1] $end
$var wire 1 1 c_0 [1:1] $end
$scope begin addbit $end
$scope begin genblk2 $end
$scope module muxes $end
$var wire 3 2 a [2:0] $end
$var wire 3 3 b [2:0] $end
$var wire 1 4 sel $end
$var wire 3 5 out [2:0] $end
$scope begin addbit[0] $end
$upscope $end
$scope begin addbit[1] $end
$upscope $end
$scope begin addbit[2] $end
$upscope $end
$upscope $end
$scope module rca_0 $end
$var wire 2 6 a [1:0] $end
$var wire 2 7 b [1:0] $end
$var wire 1 8 ci $end
$var wire 2 9 s [1:0] $end
$var wire 1 1 co $end
$var wire 3 : c [2:0] $end
$scope begin addbit[0] $end
$scope module f $end
$var wire 1 ; A $end
$var wire 1 < B $end
$var wire 1 = S $end
$var wire 1 > cin $end
$var wire 1 ? cout $end
$var wire 1 @ w1 $end
$var wire 1 A w2 $end
$var wire 1 B w3 $end
$var wire 1 C w4 $end
$upscope $end
$upscope $end
$scope begin addbit[1] $end
$scope module f $end
$var wire 1 D A $end
$var wire 1 E B $end
$var wire 1 F S $end
$var wire 1 G cin $end
$var wire 1 H cout $end
$var wire 1 I w1 $end
$var wire 1 J w2 $end
$var wire 1 K w3 $end
$var wire 1 L w4 $end
$upscope $end
$upscope $end
$upscope $end
$scope module rca_1 $end
$var wire 2 M a [1:0] $end
$var wire 2 N b [1:0] $end
$var wire 1 O ci $end
$var wire 2 P s [1:0] $end
$var wire 1 0 co $end
$var wire 3 Q c [2:0] $end
$scope begin addbit[0] $end
$scope module f $end
$var wire 1 R A $end
$var wire 1 S B $end
$var wire 1 T S $end
$var wire 1 U cin $end
$var wire 1 V cout $end
$var wire 1 W w1 $end
$var wire 1 X w2 $end
$var wire 1 Y w3 $end
$var wire 1 Z w4 $end
$upscope $end
$upscope $end
$scope begin addbit[1] $end
$scope module f $end
$var wire 1 [ A $end
$var wire 1 \ B $end
$var wire 1 ] S $end
$var wire 1 ^ cin $end
$var wire 1 _ cout $end
$var wire 1 ` w1 $end
$var wire 1 a w2 $end
$var wire 1 b w3 $end
$var wire 1 c w4 $end
$upscope $end
$upscope $end
$upscope $end
$upscope $end
$scope module rca_initial $end
$var wire 2 d a [1:0] $end
$var wire 2 e b [1:0] $end
$var wire 1 ( ci $end
$var wire 2 f s [1:0] $end
$var wire 1 4 co $end
$var wire 3 g c [2:0] $end
$scope begin addbit[0] $end
$scope module f $end
$var wire 1 h A $end
$var wire 1 i B $end
$var wire 1 j S $end
$var wire 1 k cin $end
$var wire 1 l cout $end
$var wire 1 m w1 $end
$var wire 1 n w2 $end
$var wire 1 o w3 $end
$var wire 1 p w4 $end
$upscope $end
$upscope $end
$scope begin addbit[1] $end
$scope module f $end
$var wire 1 q A $end
$var wire 1 r B $end
$var wire 1 s S $end
$var wire 1 t cin $end
$var wire 1 u cout $end
$var wire 1 v w1 $end
$var wire 1 w w2 $end
$var wire 1 x w3 $end
$var wire 1 y w4 $end
$upscope $end
$upscope $end
$upscope $end
$upscope $end
$upscope $end
$upscope $end
$enddefinitions $end
#0
$dumpvars
xy
xx
xw
xv
xu
xt
xs
xr
xq
0p
0o
xn
xm
xl
0k
xj
xi
xh
bx0 g
bx f
bx e
bx d
xc
xb
xa
x`
x_
x^
x]
x\
x[
xZ
xY
xX
xW
xV
1U
xT
xS
xR
bx1 Q
bx P
1O
bx N
bx M
xL
xK
xJ
xI
xH
xG
xF
xE
xD
0C
0B
xA
x@
x?
0>
x=
x<
x;
bx0 :
bx 9
08
bx 7
bx 6
bx 5
x4
bx 3
bx 2
x1
x0
bx /
bx .
bx -
bx ,
bx +
b0 *
b0 )
0(
bx '
bx &
x%
x$
bx #
bx "
x!
$end
#5
0!
0%
b0 5
0s
0F
0]
0t
04
0G
01
0^
00
b0 "
b0 /
b0 f
0j
0l
b0 g
0u
b0 2
b0 .
b0 9
0=
0?
b0 :
0H
b1 3
b1 -
b1 P
1T
0V
b1 Q
0_
0x
0K
0Y
0b
0m
0n
0v
0w
0y
0@
0A
0I
0J
0L
0W
0X
0Z
0`
0a
0c
0h
0q
0;
0D
0R
0[
0i
0r
0<
0E
0S
0\
b0 #
0$
b0 d
b0 6
b0 M
b0 e
b0 7
b0 N
b1 *
b0 &
b0 +
b0 '
b0 ,
#10
b1 "
b1 /
b1 f
1j
1m
0!
1i
b1 #
b1 e
b10 *
b1 '
b1 ,
#15
0j
b10 "
b10 /
b10 f
1s
0m
1v
0!
0i
1r
b10 #
b10 e
b11 *
b10 '
b10 ,
#20
b11 "
b11 /
b11 f
1j
1m
0!
1i
b11 #
b11 e
b100 *
b11 '
b11 ,
#25
b1 5
1]
1^
0j
b100 "
b100 /
b0 f
0s
b1 2
b1 .
b1 9
1=
b10 3
b10 -
b10 P
0T
b11 Q
1V
0m
0v
1@
1W
1Z
0!
0i
0r
1<
1S
b100 #
b0 e
b1 7
b1 N
b101 *
b100 '
b100 ,
#30
b101 "
b101 /
b1 f
1j
1m
0!
1i
b101 #
b1 e
b110 *
b101 '
b101 ,
#35
0j
b110 "
b110 /
b10 f
1s
0m
1v
0!
0i
1r
b110 #
b10 e
b111 *
b110 '
b110 ,
#40
b111 "
b111 /
b11 f
1j
1m
0!
1i
b111 #
b11 e
b1000 *
b111 '
b111 ,
#45
b10 5
0^
00
0j
b1000 "
b1000 /
b0 f
0s
0=
b10 2
b10 .
b10 9
1F
1T
0V
b11 3
b11 -
b11 P
1]
b1 Q
0_
0m
0v
0@
1I
0W
0Z
1`
0c
0!
0i
0r
0<
1E
0S
1\
b1000 #
b0 e
b10 7
b10 N
b1001 *
b1000 '
b1000 ,
#50
b1001 "
b1001 /
b1 f
1j
1m
0!
1i
b1001 #
b1 e
b1010 *
b1001 '
b1001 ,
#55
0j
b1010 "
b1010 /
b10 f
1s
0m
1v
0!
0i
1r
b1010 #
b10 e
b1011 *
b1010 '
b1010 ,
#60
b1011 "
b1011 /
b11 f
1j
1m
0!
1i
b1011 #
b11 e
b1100 *
b1011 '
b1011 ,
#65
10
b11 5
1_
0]
1c
1^
0j
b1100 "
b1100 /
b0 f
0s
b11 2
b11 .
b11 9
1=
b100 3
b0 -
b0 P
0T
b111 Q
1V
0m
0v
1@
1W
1Z
0!
0i
0r
1<
1S
b1100 #
b0 e
b11 7
b11 N
b1101 *
b1100 '
b1100 ,
#70
b1101 "
b1101 /
b1 f
1j
1m
0!
1i
b1101 #
b1 e
b1110 *
b1101 '
b1101 ,
#75
0j
b1110 "
b1110 /
b10 f
1s
0m
1v
0!
0i
1r
b1110 #
b10 e
b1111 *
b1110 '
b1110 ,
#80
b1111 "
b1111 /
b11 f
1j
1m
0!
1i
b1111 #
b11 e
b1 )
b0 *
b1111 '
b1111 ,
#85
b0 5
0^
00
b1 "
b1 /
b1 f
0s
0=
b0 2
b0 .
b0 9
0F
1T
0V
b1 3
b1 -
b1 P
0]
b1 Q
0_
0v
0@
0I
0W
0Z
0`
0c
1h
0!
0i
0r
0<
0E
0S
0\
b1 d
b1 #
b0 e
b0 7
b0 N
b1 *
b1 &
b1 +
b0 '
b0 ,
#90
1s
1t
b10 "
b10 /
b10 f
0j
b10 g
1l
0m
1n
0!
1i
b10 #
b1 e
b10 *
b1 '
b1 ,
#95
b0 5
0t
04
1j
0l
b11 "
b11 /
b11 f
1s
b0 g
0u
1m
0n
1v
0y
0!
0i
1r
b11 #
b10 e
b11 *
b10 '
b10 ,
#100
b1 5
14
1u
0s
1y
1t
b100 "
b100 /
b0 f
0j
b110 g
1l
0m
1n
0!
1i
b100 #
b11 e
b100 *
b11 '
b11 ,
#105
b1 5
1]
0t
04
1^
1j
0l
b101 "
b101 /
b1 f
0s
b0 g
0u
b1 2
b1 .
b1 9
1=
b10 3
b10 -
b10 P
0T
b11 Q
1V
1m
0n
0v
0y
1@
1W
1Z
0!
0i
0r
1<
1S
b101 #
b0 e
b1 7
b1 N
b101 *
b100 '
b100 ,
#110
1s
1t
b110 "
b110 /
b10 f
0j
b10 g
1l
0m
1n
0!
1i
b110 #
b1 e
b110 *
b101 '
b101 ,
#115
b1 5
0t
04
1j
0l
b111 "
b111 /
b11 f
1s
b0 g
0u
1m
0n
1v
0y
0!
0i
1r
b111 #
b10 e
b111 *
b110 '
b110 ,
#120
b10 5
14
1u
0s
1y
1t
b1000 "
b1000 /
b0 f
0j
b110 g
1l
0m
1n
0!
1i
b1000 #
b11 e
b1000 *
b111 '
b111 ,
#125
b10 5
0t
04
0^
00
1j
0l
b1001 "
b1001 /
b1 f
0s
b0 g
0u
0=
b10 2
b10 .
b10 9
1F
1T
0V
b11 3
b11 -
b11 P
1]
b1 Q
0_
1m
0n
0v
0y
0@
1I
0W
0Z
1`
0c
0!
0i
0r
0<
1E
0S
1\
b1001 #
b0 e
b10 7
b10 N
b1001 *
b1000 '
b1000 ,
#130
1s
1t
b1010 "
b1010 /
b10 f
0j
b10 g
1l
0m
1n
0!
1i
b1010 #
b1 e
b1010 *
b1001 '
b1001 ,
#135
b10 5
0t
04
1j
0l
b1011 "
b1011 /
b11 f
1s
b0 g
0u
1m
0n
1v
0y
0!
0i
1r
b1011 #
b10 e
b1011 *
b1010 '
b1010 ,
#140
b11 5
14
1u
0s
1y
1t
b1100 "
b1100 /
b0 f
0j
b110 g
1l
0m
1n
0!
1i
b1100 #
b11 e
b1100 *
b1011 '
b1011 ,
#145
10
b11 5
1_
0]
1c
0t
04
1^
1j
0l
b1101 "
b1101 /
b1 f
0s
b0 g
0u
b11 2
b11 .
b11 9
1=
b100 3
b0 -
b0 P
0T
b111 Q
1V
1m
0n
0v
0y
1@
1W
1Z
0!
0i
0r
1<
1S
b1101 #
b0 e
b11 7
b11 N
b1101 *
b1100 '
b1100 ,
#150
1s
1t
b1110 "
b1110 /
b10 f
0j
b10 g
1l
0m
1n
0!
1i
b1110 #
b1 e
b1110 *
b1101 '
b1101 ,
#155
0%
b11 5
0t
04
1j
0l
b1111 "
b1111 /
b11 f
1s
b0 g
0u
1m
0n
1v
0y
0!
0i
1r
b1111 #
b10 e
b1111 *
b1110 '
b1110 ,
#160
1%
b100 5
14
1u
0s
1y
1t
b0 "
b0 /
b0 f
0j
b110 g
1l
0m
1n
0!
1i
b0 #
1$
b11 e
b10 )
b0 *
b1111 '
b1111 ,
#165
0%
04
0u
b0 5
b10 "
b10 /
b10 f
1s
0t
0^
00
b0 g
0l
0=
b0 2
b0 .
b0 9
0F
1T
0V
b1 3
b1 -
b1 P
0]
b1 Q
0_
0x
0n
0y
0@
0I
0W
0Z
0`
0c
0h
1q
0!
0i
0r
0<
0E
0S
0\
b10 d
b10 #
0$
b0 e
b0 7
b0 N
b1 *
b10 &
b10 +
b0 '
b0 ,
#170
b11 "
b11 /
b11 f
1j
1m
0!
1i
b11 #
b1 e
b10 *
b1 '
b1 ,
#175
b1 5
14
0j
b100 "
b100 /
b0 f
0s
b100 g
1u
0m
0v
1w
0!
0i
1r
b100 #
b10 e
b11 *
b10 '
b10 ,
#180
b101 "
b101 /
b1 f
1j
1m
0!
1i
b101 #
b11 e
b100 *
b11 '
b11 ,
#185
b1 5
1]
04
1^
0j
b110 "
b110 /
b10 f
1s
b0 g
0u
b1 2
b1 .
b1 9
1=
b10 3
b10 -
b10 P
0T
b11 Q
1V
0m
1v
0w
1@
1W
1Z
0!
0i
0r
1<
1S
b110 #
b0 e
b1 7
b1 N
b101 *
b100 '
b100 ,
#190
b111 "
b111 /
b11 f
1j
1m
0!
1i
b111 #
b1 e
b110 *
b101 '
b101 ,
#195
b10 5
14
0j
b1000 "
b1000 /
b0 f
0s
b100 g
1u
0m
0v
1w
0!
0i
1r
b1000 #
b10 e
b111 *
b110 '
b110 ,
#200
b1001 "
b1001 /
b1 f
1j
1m
0!
1i
b1001 #
b11 e
b1000 *
b111 '
b111 ,
#205
b10 5
04
0^
00
0j
b1010 "
b1010 /
b10 f
1s
b0 g
0u
0=
b10 2
b10 .
b10 9
1F
1T
0V
b11 3
b11 -
b11 P
1]
b1 Q
0_
0m
1v
0w
0@
1I
0W
0Z
1`
0c
0!
0i
0r
0<
1E
0S
1\
b1010 #
b0 e
b10 7
b10 N
b1001 *
b1000 '
b1000 ,
#210
b1011 "
b1011 /
b11 f
1j
1m
0!
1i
b1011 #
b1 e
b1010 *
b1001 '
b1001 ,
#215
b11 5
14
0j
b1100 "
b1100 /
b0 f
0s
b100 g
1u
0m
0v
1w
0!
0i
1r
b1100 #
b10 e
b1011 *
b1010 '
b1010 ,
#220
b1101 "
b1101 /
b1 f
1j
1m
0!
1i
b1101 #
b11 e
b1100 *
b1011 '
b1011 ,
#225
10
b11 5
1_
0]
1c
04
1^
0j
b1110 "
b1110 /
b10 f
1s
b0 g
0u
b11 2
b11 .
b11 9
1=
b100 3
b0 -
b0 P
0T
b111 Q
1V
0m
1v
0w
1@
1W
1Z
0!
0i
0r
1<
1S
b1110 #
b0 e
b11 7
b11 N
b1101 *
b1100 '
b1100 ,
#230
b1111 "
b1111 /
b11 f
1j
1m
0!
1i
b1111 #
b1 e
b1110 *
b1101 '
b1101 ,
#235
1%
b100 5
14
0j
b0 "
b0 /
b0 f
0s
b100 g
1u
0m
0v
1w
0!
0i
1r
b0 #
1$
b10 e
b1111 *
b1110 '
b1110 ,
#240
b1 "
b1 /
b1 f
1j
1m
0!
1i
b1 #
b11 e
b11 )
b0 *
b1111 '
b1111 ,
#245
0%
b0 5
04
0^
00
b11 "
b11 /
b11 f
1s
b0 g
0u
0=
b0 2
b0 .
b0 9
0F
1T
0V
b1 3
b1 -
b1 P
0]
b1 Q
0_
1v
0w
0@
0I
0W
0Z
0`
0c
1h
0!
0i
0r
0<
0E
0S
0\
b11 d
b11 #
0$
b0 e
b0 7
b0 N
b1 *
b11 &
b11 +
b0 '
b0 ,
#250
b1 5
14
1u
0s
1x
1t
b100 "
b100 /
b0 f
0j
b110 g
1l
0m
1n
0!
1i
b100 #
b1 e
b10 *
b1 '
b1 ,
#255
0x
0t
1j
b100 g
0l
b101 "
b101 /
b1 f
0s
1m
0n
0v
1w
0y
0!
0i
1r
b101 #
b10 e
b11 *
b10 '
b10 ,
#260
1s
1x
1y
1t
b110 "
b110 /
b10 f
0j
b110 g
1l
0m
1n
0!
1i
b110 #
b11 e
b100 *
b11 '
b11 ,
#265
04
0u
b1 5
0x
1]
0t
1^
1j
b0 g
0l
b111 "
b111 /
b11 f
1s
b1 2
b1 .
b1 9
1=
b10 3
b10 -
b10 P
0T
b11 Q
1V
1m
0n
1v
0w
0y
1@
1W
1Z
0!
0i
0r
1<
1S
b111 #
b0 e
b1 7
b1 N
b101 *
b100 '
b100 ,
#270
b10 5
14
1u
0s
1x
1t
b1000 "
b1000 /
b0 f
0j
b110 g
1l
0m
1n
0!
1i
b1000 #
b1 e
b110 *
b101 '
b101 ,
#275
0x
0t
1j
b100 g
0l
b1001 "
b1001 /
b1 f
0s
1m
0n
0v
1w
0y
0!
0i
1r
b1001 #
b10 e
b111 *
b110 '
b110 ,
#280
1s
1x
1y
1t
b1010 "
b1010 /
b10 f
0j
b110 g
1l
0m
1n
0!
1i
b1010 #
b11 e
b1000 *
b111 '
b111 ,
#285
0%
04
0u
b10 5
0x
0t
0^
00
1j
b0 g
0l
b1011 "
b1011 /
b11 f
1s
0=
b10 2
b10 .
b10 9
1F
1T
0V
b11 3
b11 -
b11 P
1]
b1 Q
0_
1m
0n
1v
0w
0y
0@
1I
0W
0Z
1`
0c
0!
0i
0r
0<
1E
0S
1\
b1011 #
b0 e
b10 7
b10 N
b1001 *
b1000 '
b1000 ,
#290
b11 5
14
1u
0s
1x
1t
b1100 "
b1100 /
b0 f
0j
b110 g
1l
0m
1n
0!
1i
b1100 #
b1 e
b1010 *
b1001 '
b1001 ,
#295
0x
0t
1j
b100 g
0l
b1101 "
b1101 /
b1 f
0s
1m
0n
0v
1w
0y
0!
0i
1r
b1101 #
b10 e
b1011 *
b1010 '
b1010 ,
#300
1s
1x
1y
1t
b1110 "
b1110 /
b10 f
0j
b110 g
1l
0m
1n
0!
1i
b1110 #
b11 e
b1100 *
b1011 '
b1011 ,
#305
04
10
0u
b11 5
1_
0x
0]
1c
0t
1^
1j
b0 g
0l
b1111 "
b1111 /
b11 f
1s
b11 2
b11 .
b11 9
1=
b100 3
b0 -
b0 P
0T
b111 Q
1V
1m
0n
1v
0w
0y
1@
1W
1Z
0!
0i
0r
1<
1S
b1111 #
b0 e
b11 7
b11 N
b1101 *
b1100 '
b1100 ,
#310
1%
b100 5
14
1u
0s
1x
1t
b0 "
b0 /
b0 f
0j
b110 g
1l
0m
1n
0!
1i
b0 #
1$
b1 e
b1110 *
b1101 '
b1101 ,
#315
0x
0t
1j
b100 g
0l
b1 "
b1 /
b1 f
0s
1m
0n
0v
1w
0y
0!
0i
1r
b1 #
b10 e
b1111 *
b1110 '
b1110 ,
#320
1s
1x
1y
1t
b10 "
b10 /
b10 f
0j
b110 g
1l
0m
1n
0!
1i
b10 #
b11 e
b100 )
b0 *
b1111 '
b1111 ,
#325
0%
b1 5
b100 "
b100 /
b0 f
0s
0t
04
00
0l
b0 g
0u
b1 2
b1 .
b1 9
0F
b10 3
b10 -
b10 P
1]
b11 Q
0_
0x
1Y
0n
0w
0y
0I
0Z
0`
0c
0h
0q
1;
1R
0!
0i
0r
0<
0E
0S
0\
b0 d
b1 6
b1 M
b100 #
0$
b0 e
b0 7
b0 N
b1 *
b100 &
b100 +
b0 '
b0 ,
#330
b101 "
b101 /
b1 f
1j
1m
0!
1i
b101 #
b1 e
b10 *
b1 '
b1 ,
#335
0j
b110 "
b110 /
b10 f
1s
0m
1v
0!
0i
1r
b110 #
b10 e
b11 *
b10 '
b10 ,
#340
b111 "
b111 /
b11 f
1j
1m
0!
1i
b111 #
b11 e
b100 *
b11 '
b11 ,
#345
b10 5
1F
1G
0j
b1000 "
b1000 /
b0 f
0s
b10 2
b10 .
b10 9
0=
b10 :
1?
b11 3
b11 -
b11 P
1T
0m
0v
0@
1A
0W
1X
1Z
0!
0i
0r
1<
1S
b1000 #
b0 e
b1 7
b1 N
b101 *
b100 '
b100 ,
#350
b1001 "
b1001 /
b1 f
1j
1m
0!
1i
b1001 #
b1 e
b110 *
b101 '
b101 ,
#355
0j
b1010 "
b1010 /
b10 f
1s
0m
1v
0!
0i
1r
b1010 #
b10 e
b111 *
b110 '
b110 ,
#360
b1011 "
b1011 /
b11 f
1j
1m
0!
1i
b1011 #
b11 e
b1000 *
b111 '
b111 ,
#365
0%
b11 5
0G
01
10
0j
b1100 "
b1100 /
b0 f
0s
1=
0?
b11 2
b11 .
b11 9
1F
b0 :
0H
0T
b100 3
b0 -
b0 P
0]
b111 Q
1_
0m
0v
1@
0A
1I
0L
1W
0X
0Z
1`
1c
0!
0i
0r
0<
1E
0S
1\
b1100 #
b0 e
b10 7
b10 N
b1001 *
b1000 '
b1000 ,
#370
b1101 "
b1101 /
b1 f
1j
1m
0!
1i
b1101 #
b1 e
b1010 *
b1001 '
b1001 ,
#375
0j
b1110 "
b1110 /
b10 f
1s
0m
1v
0!
0i
1r
b1110 #
b10 e
b1011 *
b1010 '
b1010 ,
#380
b1111 "
b1111 /
b11 f
1j
1m
0!
1i
b1111 #
b11 e
b1100 *
b1011 '
b1011 ,
#385
1%
11
b100 5
1H
0F
1L
1G
0j
b0 "
b0 /
b0 f
0s
b100 2
b0 .
b0 9
0=
b110 :
1?
b101 3
b1 -
b1 P
1T
0m
0v
0@
1A
0W
1X
1Z
0!
0i
0r
1<
1S
b0 #
1$
b0 e
b11 7
b11 N
b1101 *
b1100 '
b1100 ,
#390
b1 "
b1 /
b1 f
1j
1m
0!
1i
b1 #
b1 e
b1110 *
b1101 '
b1101 ,
#395
0j
b10 "
b10 /
b10 f
1s
0m
1v
0!
0i
1r
b10 #
b10 e
b1111 *
b1110 '
b1110 ,
#400
b11 "
b11 /
b11 f
1j
1m
0!
1i
b11 #
b11 e
b101 )
b0 *
b1111 '
b1111 ,
#405
0%
b1 5
0G
01
00
b101 "
b101 /
b1 f
0s
1=
0?
b1 2
b1 .
b1 9
0F
b0 :
0H
0T
b10 3
b10 -
b10 P
1]
b11 Q
0_
0v
1@
0A
0I
0L
1W
0X
0Z
0`
0c
1h
0!
0i
0r
0<
0E
0S
0\
b1 d
b101 #
0$
b0 e
b0 7
b0 N
b1 *
b101 &
b101 +
b0 '
b0 ,
#410
1s
1t
b110 "
b110 /
b10 f
0j
b10 g
1l
0m
1n
0!
1i
b110 #
b1 e
b10 *
b1 '
b1 ,
#415
b1 5
0t
04
1j
0l
b111 "
b111 /
b11 f
1s
b0 g
0u
1m
0n
1v
0y
0!
0i
1r
b111 #
b10 e
b11 *
b10 '
b10 ,
#420
b10 5
14
1u
0s
1y
1t
b1000 "
b1000 /
b0 f
0j
b110 g
1l
0m
1n
0!
1i
b1000 #
b11 e
b100 *
b11 '
b11 ,
#425
1F
0t
04
1G
1j
0l
b1001 "
b1001 /
b1 f
0s
b0 g
0u
b10 2
b10 .
b10 9
0=
b10 :
1?
b11 3
b11 -
b11 P
1T
1m
0n
0v
0y
0@
1A
0W
1X
1Z
0!
0i
0r
1<
1S
b1001 #
b0 e
b1 7
b1 N
b101 *
b100 '
b100 ,
#430
1s
1t
b1010 "
b1010 /
b10 f
0j
b10 g
1l
0m
1n
0!
1i
b1010 #
b1 e
b110 *
b101 '
b101 ,
#435
b10 5
0t
04
1j
0l
b1011 "
b1011 /
b11 f
1s
b0 g
0u
1m
0n
1v
0y
0!
0i
1r
b1011 #
b10 e
b111 *
b110 '
b110 ,
#440
b11 5
14
1u
0s
1y
1t
b1100 "
b1100 /
b0 f
0j
b110 g
1l
0m
1n
0!
1i
b1100 #
b11 e
b1000 *
b111 '
b111 ,
#445
0%
b11 5
0t
04
0G
01
10
1j
0l
b1101 "
b1101 /
b1 f
0s
b0 g
0u
1=
0?
b11 2
b11 .
b11 9
1F
b0 :
0H
0T
b100 3
b0 -
b0 P
0]
b111 Q
1_
1m
0n
0v
0y
1@
0A
1I
0L
1W
0X
0Z
1`
1c
0!
0i
0r
0<
1E
0S
1\
b1101 #
b0 e
b10 7
b10 N
b1001 *
b1000 '
b1000 ,
#450
1s
1t
b1110 "
b1110 /
b10 f
0j
b10 g
1l
0m
1n
0!
1i
b1110 #
b1 e
b1010 *
b1001 '
b1001 ,
#455
0%
b11 5
0t
04
1j
0l
b1111 "
b1111 /
b11 f
1s
b0 g
0u
1m
0n
1v
0y
0!
0i
1r
b1111 #
b10 e
b1011 *
b1010 '
b1010 ,
#460
1%
b100 5
14
1u
0s
1y
1t
b0 "
b0 /
b0 f
0j
b110 g
1l
0m
1n
0!
1i
b0 #
1$
b11 e
b1100 *
b1011 '
b1011 ,
#465
1%
11
b100 5
1H
0F
1L
0t
04
1G
1j
0l
b1 "
b1 /
b1 f
0s
b0 g
0u
b100 2
b0 .
b0 9
0=
b110 :
1?
b101 3
b1 -
b1 P
1T
1m
0n
0v
0y
0@
1A
0W
1X
1Z
0!
0i
0r
1<
1S
b1 #
b0 e
b11 7
b11 N
b1101 *
b1100 '
b1100 ,
#470
1s
1t
b10 "
b10 /
b10 f
0j
b10 g
1l
0m
1n
0!
1i
b10 #
b1 e
b1110 *
b1101 '
b1101 ,
#475
b100 5
0t
04
1j
0l
b11 "
b11 /
b11 f
1s
b0 g
0u
1m
0n
1v
0y
0!
0i
1r
b11 #
b10 e
b1111 *
b1110 '
b1110 ,
#480
b101 5
14
1u
0s
1y
1t
b100 "
b100 /
b0 f
0j
b110 g
1l
0m
1n
0!
1i
b100 #
b11 e
b110 )
b0 *
b1111 '
b1111 ,
#485
0%
04
0u
b1 5
b110 "
b110 /
b10 f
1s
0t
0G
01
00
b0 g
0l
1=
0?
b1 2
b1 .
b1 9
0F
b0 :
0H
0T
b10 3
b10 -
b10 P
1]
b11 Q
0_
0x
0n
0y
1@
0A
0I
0L
1W
0X
0Z
0`
0c
0h
1q
0!
0i
0r
0<
0E
0S
0\
b10 d
b110 #
0$
b0 e
b0 7
b0 N
b1 *
b110 &
b110 +
b0 '
b0 ,
#490
b111 "
b111 /
b11 f
1j
1m
0!
1i
b111 #
b1 e
b10 *
b1 '
b1 ,
#495
b10 5
14
0j
b1000 "
b1000 /
b0 f
0s
b100 g
1u
0m
0v
1w
0!
0i
1r
b1000 #
b10 e
b11 *
b10 '
b10 ,
#500
b1001 "
b1001 /
b1 f
1j
1m
0!
1i
b1001 #
b11 e
b100 *
b11 '
b11 ,
