src/FA.v
// file: FA.v
// author: @refaay

`timescale 1ns/1ns

module FA(input A, input B, input cin, output S, output cout);
wire w1, w2, w3, w4;
xor xor1 (w1, A, B);
xor xor2 (S, w1, cin);
and and1 (w2, A, B);
and and2 (w3, A, cin);
and and3 (w4, B, cin);
or or1 (cout, w2, w3, w4);
endmodule

src/rca_n.v
// file: rca_n.v
// author: @refaay

`timescale 1ns/1ns

module rca_n(a, b, ci, s, co);
parameter n = 32; // Default
input [n-1:0] a, b;
input ci;
output [n-1:0] s;
output co;
wire [n:0] c;
assign c[0] = ci;
assign co = c[n];
genvar i;
generate
for (i=0; i<n; i=i+1) begin: addbit
FA f (a[i], b[i], c[i], s[i], c[i+1]); // FA fa (.A(a[i]), .B(b[i], .cin(c[i]), .S(s[i]), .cout(c[i+1]));
end
endgenerate
endmodule

src/rca_n_tb.v
// file: rca_n_tb.v
// author: @refaay
// Testbench for rca_n

`timescale 1ns/1ns

module rca_n_tb;

	//Inputs
	reg [3: 0] a;
	reg [3: 0] b;
	reg ci;


	//Outputs
	wire [3: 0] s, ref_s;
	wire co, ref_co;
	wire err;


	//Instantiation of Unit Under Test
	rca_n uut (
		.a(a),
		.b(b),
		.ci(ci),
		.s(s),
		.co(co)
	);


	
	// Golden Model
    assign {ref_co, ref_s} = a + b + ci;
    
    // Checker
    assign err = (ref_s != s) || (ref_co != co);


	// Stimulu Generator
    integer A_i, B_i;
    initial begin
    ci = 0;
    for(A_i=0; A_i<16; A_i=A_i+1)
    for(B_i=0; B_i<16; B_i=B_i+1) begin
    #5 b = B_i;
    a = A_i;
    end
    #10;
    ci = 1;
    for(A_i=0; A_i<16; A_i=A_i+1)
    for(B_i=0; B_i<16; B_i=B_i+1) begin
    #5 b = B_i;
    a = A_i;
   
    end
    
    end


endmodule

build (read-only)/rca_n_tb.vcd
$date
	Thu Feb 15 19:27:52 2018
$end
$version
	Icarus Verilog
$end
$timescale
	1ns
$end
$scope module rca_n_tb $end
$var wire 1 ! err $end
$var wire 4 " s [3:0] $end
$var wire 4 # ref_s [3:0] $end
$var wire 1 $ ref_co $end
$var wire 1 % co $end
$var reg 4 & a [3:0] $end
$var reg 4 ' b [3:0] $end
$var reg 1 ( ci $end
$var integer 32 ) A_i [31:0] $end
$var integer 32 * B_i [31:0] $end
$scope module uut $end
$var wire 32 + a [31:0] $end
$var wire 32 , b [31:0] $end
$var wire 1 ( ci $end
$var wire 32 - s [31:0] $end
$var wire 1 % co $end
$var wire 33 . c [32:0] $end
$scope begin addbit[0] $end
$scope module f $end
$var wire 1 / A $end
$var wire 1 0 B $end
$var wire 1 1 S $end
$var wire 1 2 cin $end
$var wire 1 3 cout $end
$var wire 1 4 w1 $end
$var wire 1 5 w2 $end
$var wire 1 6 w3 $end
$var wire 1 7 w4 $end
$upscope $end
$upscope $end
$scope begin addbit[1] $end
$scope module f $end
$var wire 1 8 A $end
$var wire 1 9 B $end
$var wire 1 : S $end
$var wire 1 ; cin $end
$var wire 1 < cout $end
$var wire 1 = w1 $end
$var wire 1 > w2 $end
$var wire 1 ? w3 $end
$var wire 1 @ w4 $end
$upscope $end
$upscope $end
$scope begin addbit[2] $end
$scope module f $end
$var wire 1 A A $end
$var wire 1 B B $end
$var wire 1 C S $end
$var wire 1 D cin $end
$var wire 1 E cout $end
$var wire 1 F w1 $end
$var wire 1 G w2 $end
$var wire 1 H w3 $end
$var wire 1 I w4 $end
$upscope $end
$upscope $end
$scope begin addbit[3] $end
$scope module f $end
$var wire 1 J A $end
$var wire 1 K B $end
$var wire 1 L S $end
$var wire 1 M cin $end
$var wire 1 N cout $end
$var wire 1 O w1 $end
$var wire 1 P w2 $end
$var wire 1 Q w3 $end
$var wire 1 R w4 $end
$upscope $end
$upscope $end
$scope begin addbit[4] $end
$scope module f $end
$var wire 1 S A $end
$var wire 1 T B $end
$var wire 1 U S $end
$var wire 1 V cin $end
$var wire 1 W cout $end
$var wire 1 X w1 $end
$var wire 1 Y w2 $end
$var wire 1 Z w3 $end
$var wire 1 [ w4 $end
$upscope $end
$upscope $end
$scope begin addbit[5] $end
$scope module f $end
$var wire 1 \ A $end
$var wire 1 ] B $end
$var wire 1 ^ S $end
$var wire 1 _ cin $end
$var wire 1 ` cout $end
$var wire 1 a w1 $end
$var wire 1 b w2 $end
$var wire 1 c w3 $end
$var wire 1 d w4 $end
$upscope $end
$upscope $end
$scope begin addbit[6] $end
$scope module f $end
$var wire 1 e A $end
$var wire 1 f B $end
$var wire 1 g S $end
$var wire 1 h cin $end
$var wire 1 i cout $end
$var wire 1 j w1 $end
$var wire 1 k w2 $end
$var wire 1 l w3 $end
$var wire 1 m w4 $end
$upscope $end
$upscope $end
$scope begin addbit[7] $end
$scope module f $end
$var wire 1 n A $end
$var wire 1 o B $end
$var wire 1 p S $end
$var wire 1 q cin $end
$var wire 1 r cout $end
$var wire 1 s w1 $end
$var wire 1 t w2 $end
$var wire 1 u w3 $end
$var wire 1 v w4 $end
$upscope $end
$upscope $end
$scope begin addbit[8] $end
$scope module f $end
$var wire 1 w A $end
$var wire 1 x B $end
$var wire 1 y S $end
$var wire 1 z cin $end
$var wire 1 { cout $end
$var wire 1 | w1 $end
$var wire 1 } w2 $end
$var wire 1 ~ w3 $end
$var wire 1 !" w4 $end
$upscope $end
$upscope $end
$scope begin addbit[9] $end
$scope module f $end
$var wire 1 "" A $end
$var wire 1 #" B $end
$var wire 1 $" S $end
$var wire 1 %" cin $end
$var wire 1 &" cout $end
$var wire 1 '" w1 $end
$var wire 1 (" w2 $end
$var wire 1 )" w3 $end
$var wire 1 *" w4 $end
$upscope $end
$upscope $end
$scope begin addbit[10] $end
$scope module f $end
$var wire 1 +" A $end
$var wire 1 ," B $end
$var wire 1 -" S $end
$var wire 1 ." cin $end
$var wire 1 /" cout $end
$var wire 1 0" w1 $end
$var wire 1 1" w2 $end
$var wire 1 2" w3 $end
$var wire 1 3" w4 $end
$upscope $end
$upscope $end
$scope begin addbit[11] $end
$scope module f $end
$var wire 1 4" A $end
$var wire 1 5" B $end
$var wire 1 6" S $end
$var wire 1 7" cin $end
$var wire 1 8" cout $end
$var wire 1 9" w1 $end
$var wire 1 :" w2 $end
$var wire 1 ;" w3 $end
$var wire 1 <" w4 $end
$upscope $end
$upscope $end
$scope begin addbit[12] $end
$scope module f $end
$var wire 1 =" A $end
$var wire 1 >" B $end
$var wire 1 ?" S $end
$var wire 1 @" cin $end
$var wire 1 A" cout $end
$var wire 1 B" w1 $end
$var wire 1 C" w2 $end
$var wire 1 D" w3 $end
$var wire 1 E" w4 $end
$upscope $end
$upscope $end
$scope begin addbit[13] $end
$scope module f $end
$var wire 1 F" A $end
$var wire 1 G" B $end
$var wire 1 H" S $end
$var wire 1 I" cin $end
$var wire 1 J" cout $end
$var wire 1 K" w1 $end
$var wire 1 L" w2 $end
$var wire 1 M" w3 $end
$var wire 1 N" w4 $end
$upscope $end
$upscope $end
$scope begin addbit[14] $end
$scope module f $end
$var wire 1 O" A $end
$var wire 1 P" B $end
$var wire 1 Q" S $end
$var wire 1 R" cin $end
$var wire 1 S" cout $end
$var wire 1 T" w1 $end
$var wire 1 U" w2 $end
$var wire 1 V" w3 $end
$var wire 1 W" w4 $end
$upscope $end
$upscope $end
$scope begin addbit[15] $end
$scope module f $end
$var wire 1 X" A $end
$var wire 1 Y" B $end
$var wire 1 Z" S $end
$var wire 1 [" cin $end
$var wire 1 \" cout $end
$var wire 1 ]" w1 $end
$var wire 1 ^" w2 $end
$var wire 1 _" w3 $end
$var wire 1 `" w4 $end
$upscope $end
$upscope $end
$scope begin addbit[16] $end
$scope module f $end
$var wire 1 a" A $end
$var wire 1 b" B $end
$var wire 1 c" S $end
$var wire 1 d" cin $end
$var wire 1 e" cout $end
$var wire 1 f" w1 $end
$var wire 1 g" w2 $end
$var wire 1 h" w3 $end
$var wire 1 i" w4 $end
$upscope $end
$upscope $end
$scope begin addbit[17] $end
$scope module f $end
$var wire 1 j" A $end
$var wire 1 k" B $end
$var wire 1 l" S $end
$var wire 1 m" cin $end
$var wire 1 n" cout $end
$var wire 1 o" w1 $end
$var wire 1 p" w2 $end
$var wire 1 q" w3 $end
$var wire 1 r" w4 $end
$upscope $end
$upscope $end
$scope begin addbit[18] $end
$scope module f $end
$var wire 1 s" A $end
$var wire 1 t" B $end
$var wire 1 u" S $end
$var wire 1 v" cin $end
$var wire 1 w" cout $end
$var wire 1 x" w1 $end
$var wire 1 y" w2 $end
$var wire 1 z" w3 $end
$var wire 1 {" w4 $end
$upscope $end
$upscope $end
$scope begin addbit[19] $end
$scope module f $end
$var wire 1 |" A $end
$var wire 1 }" B $end
$var wire 1 ~" S $end
$var wire 1 !# cin $end
$var wire 1 "# cout $end
$var wire 1 ## w1 $end
$var wire 1 $# w2 $end
$var wire 1 %# w3 $end
$var wire 1 &# w4 $end
$upscope $end
$upscope $end
$scope begin addbit[20] $end
$scope module f $end
$var wire 1 '# A $end
$var wire 1 (# B $end
$var wire 1 )# S $end
$var wire 1 *# cin $end
$var wire 1 +# cout $end
$var wire 1 ,# w1 $end
$var wire 1 -# w2 $end
$var wire 1 .# w3 $end
$var wire 1 /# w4 $end
$upscope $end
$upscope $end
$scope begin addbit[21] $end
$scope module f $end
$var wire 1 0# A $end
$var wire 1 1# B $end
$var wire 1 2# S $end
$var wire 1 3# cin $end
$var wire 1 4# cout $end
$var wire 1 5# w1 $end
$var wire 1 6# w2 $end
$var wire 1 7# w3 $end
$var wire 1 8# w4 $end
$upscope $end
$upscope $end
$scope begin addbit[22] $end
$scope module f $end
$var wire 1 9# A $end
$var wire 1 :# B $end
$var wire 1 ;# S $end
$var wire 1 <# cin $end
$var wire 1 =# cout $end
$var wire 1 ># w1 $end
$var wire 1 ?# w2 $end
$var wire 1 @# w3 $end
$var wire 1 A# w4 $end
$upscope $end
$upscope $end
$scope begin addbit[23] $end
$scope module f $end
$var wire 1 B# A $end
$var wire 1 C# B $end
$var wire 1 D# S $end
$var wire 1 E# cin $end
$var wire 1 F# cout $end
$var wire 1 G# w1 $end
$var wire 1 H# w2 $end
$var wire 1 I# w3 $end
$var wire 1 J# w4 $end
$upscope $end
$upscope $end
$scope begin addbit[24] $end
$scope module f $end
$var wire 1 K# A $end
$var wire 1 L# B $end
$var wire 1 M# S $end
$var wire 1 N# cin $end
$var wire 1 O# cout $end
$var wire 1 P# w1 $end
$var wire 1 Q# w2 $end
$var wire 1 R# w3 $end
$var wire 1 S# w4 $end
$upscope $end
$upscope $end
$scope begin addbit[25] $end
$scope module f $end
$var wire 1 T# A $end
$var wire 1 U# B $end
$var wire 1 V# S $end
$var wire 1 W# cin $end
$var wire 1 X# cout $end
$var wire 1 Y# w1 $end
$var wire 1 Z# w2 $end
$var wire 1 [# w3 $end
$var wire 1 \# w4 $end
$upscope $end
$upscope $end
$scope begin addbit[26] $end
$scope module f $end
$var wire 1 ]# A $end
$var wire 1 ^# B $end
$var wire 1 _# S $end
$var wire 1 `# cin $end
$var wire 1 a# cout $end
$var wire 1 b# w1 $end
$var wire 1 c# w2 $end
$var wire 1 d# w3 $end
$var wire 1 e# w4 $end
$upscope $end
$upscope $end
$scope begin addbit[27] $end
$scope module f $end
$var wire 1 f# A $end
$var wire 1 g# B $end
$var wire 1 h# S $end
$var wire 1 i# cin $end
$var wire 1 j# cout $end
$var wire 1 k# w1 $end
$var wire 1 l# w2 $end
$var wire 1 m# w3 $end
$var wire 1 n# w4 $end
$upscope $end
$upscope $end
$scope begin addbit[28] $end
$scope module f $end
$var wire 1 o# A $end
$var wire 1 p# B $end
$var wire 1 q# S $end
$var wire 1 r# cin $end
$var wire 1 s# cout $end
$var wire 1 t# w1 $end
$var wire 1 u# w2 $end
$var wire 1 v# w3 $end
$var wire 1 w# w4 $end
$upscope $end
$upscope $end
$scope begin addbit[29] $end
$scope module f $end
$var wire 1 x# A $end
$var wire 1 y# B $end
$var wire 1 z# S $end
$var wire 1 {# cin $end
$var wire 1 |# cout $end
$var wire 1 }# w1 $end
$var wire 1 ~# w2 $end
$var wire 1 !$ w3 $end
$var wire 1 "$ w4 $end
$upscope $end
$upscope $end
$scope begin addbit[30] $end
$scope module f $end
$var wire 1 #$ A $end
$var wire 1 $$ B $end
$var wire 1 %$ S $end
$var wire 1 &$ cin $end
$var wire 1 '$ cout $end
$var wire 1 ($ w1 $end
$var wire 1 )$ w2 $end
$var wire 1 *$ w3 $end
$var wire 1 +$ w4 $end
$upscope $end
$upscope $end
$scope begin addbit[31] $end
$scope module f $end
$var wire 1 ,$ A $end
$var wire 1 -$ B $end
$var wire 1 .$ S $end
$var wire 1 /$ cin $end
$var wire 1 0$ cout $end
$var wire 1 1$ w1 $end
$var wire 1 2$ w2 $end
$var wire 1 3$ w3 $end
$var wire 1 4$ w4 $end
$upscope $end
$upscope $end
$upscope $end
$upscope $end
$enddefinitions $end
#0
$dumpvars
04$
03$
02$
01$
00$
0/$
0.$
0-$
0,$
0+$
0*$
0)$
0($
0'$
0&$
0%$
0$$
0#$
0"$
0!$
0~#
0}#
0|#
0{#
0z#
0y#
0x#
0w#
0v#
0u#
0t#
0s#
0r#
0q#
0p#
0o#
0n#
0m#
0l#
0k#
0j#
0i#
0h#
0g#
0f#
0e#
0d#
0c#
0b#
0a#
0`#
0_#
0^#
0]#
0\#
0[#
0Z#
0Y#
0X#
0W#
0V#
0U#
0T#
0S#
0R#
0Q#
0P#
0O#
0N#
0M#
0L#
0K#
0J#
0I#
0H#
0G#
0F#
0E#
0D#
0C#
0B#
0A#
0@#
0?#
0>#
0=#
0<#
0;#
0:#
09#
08#
07#
06#
05#
04#
03#
02#
01#
00#
0/#
0.#
0-#
0,#
0+#
0*#
0)#
0(#
0'#
0&#
0%#
0$#
0##
0"#
0!#
0~"
0}"
0|"
0{"
0z"
0y"
0x"
0w"
0v"
0u"
0t"
0s"
0r"
0q"
0p"
0o"
0n"
0m"
0l"
0k"
0j"
0i"
0h"
0g"
0f"
0e"
0d"
0c"
0b"
0a"
0`"
0_"
0^"
0]"
0\"
0["
0Z"
0Y"
0X"
0W"
0V"
0U"
0T"
0S"
0R"
0Q"
0P"
0O"
0N"
0M"
0L"
0K"
0J"
0I"
0H"
0G"
0F"
0E"
0D"
0C"
0B"
0A"
0@"
0?"
0>"
0="
0<"
0;"
0:"
09"
08"
07"
06"
05"
04"
03"
02"
01"
00"
0/"
0."
0-"
0,"
0+"
0*"
0)"
0("
0'"
0&"
0%"
0$"
0#"
0""
0!"
0~
0}
0|
0{
0z
0y
0x
0w
0v
0u
0t
0s
0r
0q
0p
0o
0n
0m
0l
0k
0j
0i
0h
0g
0f
0e
0d
0c
0b
0a
0`
0_
0^
0]
0\
0[
0Z
0Y
0X
0W
xV
xU
0T
0S
xR
xQ
xP
xO
xN
xM
xL
xK
xJ
xI
xH
xG
xF
xE
xD
xC
xB
xA
x@
x?
x>
x=
x<
x;
x:
x9
x8
07
06
x5
x4
x3
02
x1
x0
x/
b0xxxx0 .
b0xxxxx -
b0xxxx ,
b0xxxx +
b0 *
b0 )
0(
bx '
bx &
0%
x$
bx #
bx "
x!
$end
#5
0!
0:
0C
0L
0U
b0 "
0;
0D
0M
0V
b0 -
01
03
0<
0E
b0 .
0N
0?
0H
0Q
04
05
0=
0>
0@
0F
0G
0I
0O
0P
0R
0/
08
0A
0J
b0 #
0$
00
09
0B
0K
b1 *
b0 +
b0 &
b0 ,
b0 '
#10
b1 "
b1 -
11
14
0!
10
b1 #
b10 *
b1 ,
b1 '
#15
b10 "
01
b10 -
1:
04
1=
0!
00
19
b10 #
b11 *
b10 ,
b10 '
#20
b11 "
b11 -
11
14
0!
10
b11 #
b100 *
b11 ,
b11 '
#25
b100 "
01
0:
b100 -
1C
04
0=
1F
0!
00
09
1B
b100 #
b101 *
b100 ,
b100 '
#30
b101 "
b101 -
11
14
0!
10
b101 #
b110 *
b101 ,
b101 '
#35
b110 "
01
b110 -
1:
04
1=
0!
00
19
b110 #
b111 *
b110 ,
b110 '
#40
b111 "
b111 -
11
14
0!
10
b111 #
b1000 *
b111 ,
b111 '
#45
b1000 "
01
0:
0C
b1000 -
1L
04
0=
0F
1O
0!
00
09
0B
1K
b1000 #
b1001 *
b1000 ,
b1000 '
#50
b1001 "
b1001 -
11
14
0!
10
b1001 #
b1010 *
b1001 ,
b1001 '
#55
b1010 "
01
b1010 -
1:
04
1=
0!
00
19
b1010 #
b1011 *
b1010 ,
b1010 '
#60
b1011 "
b1011 -
11
14
0!
10
b1011 #
b1100 *
b1011 ,
b1011 '
#65
b1100 "
01
0:
b1100 -
1C
04
0=
1F
0!
00
09
1B
b1100 #
b1101 *
b1100 ,
b1100 '
#70
b1101 "
b1101 -
11
14
0!
10
b1101 #
b1110 *
b1101 ,
b1101 '
#75
b1110 "
01
b1110 -
1:
04
1=
0!
00
19
b1110 #
b1111 *
b1110 ,
b1110 '
#80
b1111 "
b1111 -
11
14
0!
10
b1111 #
b1 )
b0 *
b1111 ,
b1111 '
#85
b1 "
0:
0C
b1 -
0L
0=
0F
0O
0!
1/
00
09
0B
0K
b1 #
b1 *
b1 +
b1 &
b0 ,
b0 '
#90
1:
b10 "
1;
b10 -
01
b10 .
13
04
15
0!
10
b10 #
b10 *
b1 ,
b1 '
#95
0C
0;
b11 "
0D
11
03
b11 -
1:
b0 .
0<
14
05
1=
0@
0!
00
19
b11 #
b11 *
b10 ,
b10 '
#100
1C
1D
1<
0:
1@
b100 "
1;
b100 -
01
b110 .
13
04
15
0!
10
b100 #
b100 *
b11 ,
b11 '
#105
0L
0;
0D
b101 "
0M
11
03
0:
0<
b101 -
1C
b0 .
0E
14
05
0=
0@
1F
0I
0!
00
09
1B
b101 #
b101 *
b100 ,
b100 '
#110
1:
b110 "
1;
b110 -
01
b10 .
13
04
15
0!
10
b110 #
b110 *
b101 ,
b101 '
#115
0L
0M
0E
1C
0I
0;
b111 "
0D
11
03
b111 -
1:
b0 .
0<
14
05
1=
0@
0!
00
19
b111 #
b111 *
b110 ,
b110 '
#120
1L
1M
1E
0C
1I
1D
1<
0:
1@
b1000 "
1;
b1000 -
01
b1110 .
13
04
15
0!
10
b1000 #
b1000 *
b111 ,
b111 '
#125
0U
0;
0D
0M
b1001 "
0V
11
03
0:
0<
0C
0E
b1001 -
1L
b0 .
0N
14
05
0=
0@
0F
0I
1O
0R
0!
00
09
0B
1K
b1001 #
b1001 *
b1000 ,
b1000 '
#130
1:
b1010 "
1;
b1010 -
01
b10 .
13
04
15
0!
10
b1010 #
b1010 *
b1001 ,
b1001 '
#135
0C
0;
b1011 "
0D
11
03
b1011 -
1:
b0 .
0<
14
05
1=
0@
0!
00
19
b1011 #
b1011 *
b1010 ,
b1010 '
#140
1C
1D
1<
0:
1@
b1100 "
1;
b1100 -
01
b110 .
13
04
15
0!
10
b1100 #
b1100 *
b1011 ,
b1011 '
#145
0U
0V
0N
1L
0R
0;
0D
b1101 "
0M
11
03
0:
0<
b1101 -
1C
b0 .
0E
14
05
0=
0@
1F
0I
0!
00
09
1B
b1101 #
b1101 *
b1100 ,
b1100 '
#150
1:
b1110 "
1;
b1110 -
01
b10 .
13
04
15
0!
10
b1110 #
b1110 *
b1101 ,
b1101 '
#155
0U
0V
0N
1L
0R
0M
0E
1C
0I
0;
b1111 "
0D
11
03
b1111 -
1:
b0 .
0<
14
05
1=
0@
0!
00
19
b1111 #
b1111 *
b1110 ,
b1110 '
#160
1U
1V
1N
0L
1R
1M
1E
0C
1I
1D
1<
0:
1@
b0 "
1;
b10000 -
01
b11110 .
13
04
15
1!
10
b0 #
1$
b10 )
b0 *
b1111 ,
b1111 '
#165
0!
0D
0<
1:
0U
0;
0M
b10 "
0V
03
0C
0E
b10 -
0L
b0 .
0N
0?
05
0@
0F
0I
0O
0R
0/
18
00
09
0B
0K
b10 #
0$
b1 *
b10 +
b10 &
b0 ,
b0 '
#170
b11 "
b11 -
11
14
0!
10
b11 #
b10 *
b1 ,
b1 '
#175
1C
b100 "
1D
01
b100 -
0:
b100 .
1<
04
0=
1>
0!
00
19
b100 #
b11 *
b10 ,
b10 '
#180
b101 "
b101 -
11
14
0!
10
b101 #
b100 *
b11 ,
b11 '
#185
0L
0D
b110 "
0M
01
1:
0<
b110 -
1C
b0 .
0E
04
1=
0>
1F
0I
0!
00
09
1B
b110 #
b101 *
b100 ,
b100 '
#190
b111 "
b111 -
11
14
0!
10
b111 #
b110 *
b101 ,
b101 '
#195
1L
1M
1E
0C
1I
b1000 "
1D
01
b1000 -
0:
b1100 .
1<
04
0=
1>
0!
00
19
b1000 #
b111 *
b110 ,
b110 '
#200
b1001 "
b1001 -
11
14
0!
10
b1001 #
b1000 *
b111 ,
b111 '
#205
0U
0D
0M
b1010 "
0V
01
1:
0<
0C
0E
b1010 -
1L
b0 .
0N
04
1=
0>
0F
0I
1O
0R
0!
00
09
0B
1K
b1010 #
b1001 *
b1000 ,
b1000 '
#210
b1011 "
b1011 -
11
14
0!
10
b1011 #
b1010 *
b1001 ,
b1001 '
#215
1C
b1100 "
1D
01
b1100 -
0:
b100 .
1<
04
0=
1>
0!
00
19
b1100 #
b1011 *
b1010 ,
b1010 '
#220
b1101 "
b1101 -
11
14
0!
10
b1101 #
b1100 *
b1011 ,
b1011 '
#225
0U
0V
0N
1L
0R
0D
b1110 "
0M
01
1:
0<
b1110 -
1C
b0 .
0E
04
1=
0>
1F
0I
0!
00
09
1B
b1110 #
b1101 *
b1100 ,
b1100 '
#230
b1111 "
b1111 -
11
14
0!
10
b1111 #
b1110 *
b1101 ,
b1101 '
#235
1U
1V
1N
0L
1R
1M
1E
0C
1I
b0 "
1D
01
b10000 -
0:
b11100 .
1<
04
0=
1>
1!
00
19
b0 #
1$
b1111 *
b1110 ,
b1110 '
#240
b1 "
b10001 -
11
14
10
b1 #
b11 )
b0 *
b1111 ,
b1111 '
#245
0!
0U
0D
0M
b11 "
0V
1:
0<
0C
0E
b11 -
0L
b0 .
0N
1=
0>
0F
0I
0O
0R
1/
00
09
0B
0K
b11 #
0$
b1 *
b11 +
b11 &
b0 ,
b0 '
#250
1C
1D
1<
0:
1?
b100 "
1;
b100 -
01
b110 .
13
04
15
0!
10
b100 #
b10 *
b1 ,
b1 '
#255
0?
0;
b101 "
11
b100 .
03
b101 -
0:
14
05
0=
1>
0@
0!
00
19
b101 #
b11 *
b10 ,
b10 '
#260
1:
1?
1@
b110 "
1;
b110 -
01
b110 .
13
04
15
0!
10
b110 #
b100 *
b11 ,
b11 '
#265
0D
0<
0?
0L
0;
b111 "
0M
11
03
1:
b111 -
1C
b0 .
0E
14
05
1=
0>
0@
1F
0I
0!
00
09
1B
b111 #
b101 *
b100 ,
b100 '
#270
1L
1M
1E
0C
1I
1D
1<
0:
1?
b1000 "
1;
b1000 -
01
b1110 .
13
04
15
0!
10
b1000 #
b110 *
b101 ,
b101 '
#275
0?
0;
b1001 "
11
b1100 .
03
b1001 -
0:
14
05
0=
1>
0@
0!
00
19
b1001 #
b111 *
b110 ,
b110 '
#280
1:
1?
1@
b1010 "
1;
b1010 -
01
b1110 .
13
04
15
0!
10
b1010 #
b1000 *
b111 ,
b111 '
#285
0D
0<
0?
0U
0;
0M
b1011 "
0V
11
03
1:
0C
0E
b1011 -
1L
b0 .
0N
14
05
1=
0>
0@
0F
0I
1O
0R
0!
00
09
0B
1K
b1011 #
b1001 *
b1000 ,
b1000 '
#290
1C
1D
1<
0:
1?
b1100 "
1;
b1100 -
01
b110 .
13
04
15
0!
10
b1100 #
b1010 *
b1001 ,
b1001 '
#295
0?
0;
b1101 "
11
b100 .
03
b1101 -
0:
14
05
0=
1>
0@
0!
00
19
b1101 #
b1011 *
b1010 ,
b1010 '
#300
1:
1?
1@
b1110 "
1;
b1110 -
01
b110 .
13
04
15
0!
10
b1110 #
b1100 *
b1011 ,
b1011 '
#305
0U
0D
0V
0<
0N
0?
1L
0R
0;
b1111 "
0M
11
03
1:
b1111 -
1C
b0 .
0E
14
05
1=
0>
0@
1F
0I
0!
00
09
1B
b1111 #
b1101 *
b1100 ,
b1100 '
#310
1U
1V
1N
0L
1R
1M
1E
0C
1I
1D
1<
0:
1?
b0 "
1;
b10000 -
01
b11110 .
13
04
15
1!
10
b0 #
1$
b1110 *
b1101 ,
b1101 '
#315
0?
0;
b1 "
11
b11100 .
03
b10001 -
0:
14
05
0=
1>
0@
00
19
b1 #
b1111 *
b1110 ,
b1110 '
#320
1:
1?
1@
b10 "
1;
b10010 -
01
b11110 .
13
04
15
10
b10 #
b100 )
b0 *
b1111 ,
b1111 '
#325
0!
0M
0E
0:
1C
0U
0;
0D
b100 "
0V
03
0<
b100 -
0L
b0 .
0N
0?
0H
05
0>
0@
0I
0O
0R
0/
08
1A
00
09
0B
0K
b100 #
0$
b1 *
b100 +
b100 &
b0 ,
b0 '
#330
b101 "
b101 -
11
14
0!
10
b101 #
b10 *
b1 ,
b1 '
#335
b110 "
01
b110 -
1:
04
1=
0!
00
19
b110 #
b11 *
b10 ,
b10 '
#340
b111 "
b111 -
11
14
0!
10
b111 #
b100 *
b11 ,
b11 '
#345
1L
b1000 "
1M
01
0:
b1000 -
0C
b1000 .
1E
04
0=
0F
1G
0!
00
09
1B
b1000 #
b101 *
b100 ,
b100 '
#350
b1001 "
b1001 -
11
14
0!
10
b1001 #
b110 *
b101 ,
b101 '
#355
b1010 "
01
b1010 -
1:
04
1=
0!
00
19
b1010 #
b111 *
b110 ,
b110 '
#360
b1011 "
b1011 -
11
14
0!
10
b1011 #
b1000 *
b111 ,
b111 '
#365
0U
0M
b1100 "
0V
01
0:
1C
0E
b1100 -
1L
b0 .
0N
04
0=
1F
0G
1O
0R
0!
00
09
0B
1K
b1100 #
b1001 *
b1000 ,
b1000 '
#370
b1101 "
b1101 -
11
14
0!
10
b1101 #
b1010 *
b1001 ,
b1001 '
#375
b1110 "
01
b1110 -
1:
04
1=
0!
00
19
b1110 #
b1011 *
b1010 ,
b1010 '
#380
b1111 "
b1111 -
11
14
0!
10
b1111 #
b1100 *
b1011 ,
b1011 '
#385
1U
1V
1N
0L
1R
b0 "
1M
01
0:
b10000 -
0C
b11000 .
1E
04
0=
0F
1G
1!
00
09
1B
b0 #
1$
b1101 *
b1100 ,
b1100 '
#390
b1 "
b10001 -
11
14
10
b1 #
b1110 *
b1101 ,
b1101 '
#395
b10 "
01
b10010 -
1:
04
1=
00
19
b10 #
b1111 *
b1110 ,
b1110 '
#400
b11 "
b10011 -
11
14
10
b11 #
b101 )
b0 *
b1111 ,
b1111 '
#405
0!
0U
0M
b101 "
0V
0:
1C
0E
b101 -
0L
b0 .
0N
0=
1F
0G
0O
0R
1/
00
09
0B
0K
b101 #
0$
b1 *
b101 +
b101 &
b0 ,
b0 '
#410
1:
b110 "
1;
b110 -
01
b10 .
13
04
15
0!
10
b110 #
b10 *
b1 ,
b1 '
#415
0L
0M
0E
1C
0H
0;
b111 "
0D
11
03
b111 -
1:
b0 .
0<
14
05
1=
0@
0!
00
19
b111 #
b11 *
b10 ,
b10 '
#420
1L
1M
1E
0C
1H
1D
1<
0:
1@
b1000 "
1;
b1000 -
01
b1110 .
13
04
15
0!
10
b1000 #
b100 *
b11 ,
b11 '
#425
0H
0;
0D
b1001 "
11
03
0:
b1000 .
0<
b1001 -
0C
14
05
0=
0@
0F
1G
0I
0!
00
09
1B
b1001 #
b101 *
b100 ,
b100 '
#430
1:
b1010 "
1;
b1010 -
01
b1010 .
13
04
15
0!
10
b1010 #
b110 *
b101 ,
b101 '
#435
0C
0H
0I
0;
b1011 "
0D
11
03
b1011 -
1:
b1000 .
0<
14
05
1=
0@
0!
00
19
b1011 #
b111 *
b110 ,
b110 '
#440
1C
1H
1I
1D
1<
0:
1@
b1100 "
1;
b1100 -
01
b1110 .
13
04
15
0!
10
b1100 #
b1000 *
b111 ,
b111 '
#445
0M
0E
0H
0U
0;
0D
b1101 "
0V
11
03
0:
0<
1C
b1101 -
1L
b0 .
0N
14
05
0=
0@
1F
0G
0I
1O
0R
0!
00
09
0B
1K
b1101 #
b1001 *
b1000 ,
b1000 '
#450
1:
b1110 "
1;
b1110 -
01
b10 .
13
04
15
0!
10
b1110 #
b1010 *
b1001 ,
b1001 '
#455
0U
0V
0N
1L
0R
0M
0E
1C
0H
0;
b1111 "
0D
11
03
b1111 -
1:
b0 .
0<
14
05
1=
0@
0!
00
19
b1111 #
b1011 *
b1010 ,
b1010 '
#460
1U
1V
1N
0L
1R
1M
1E
0C
1H
1D
1<
0:
1@
b0 "
1;
b10000 -
01
b11110 .
13
04
15
1!
10
b0 #
1$
b1100 *
b1011 ,
b1011 '
#465
0H
0;
0D
b1 "
11
03
0:
b11000 .
0<
b10001 -
0C
14
05
0=
0@
0F
1G
0I
00
09
1B
b1 #
b1101 *
b1100 ,
b1100 '
#470
1:
b10 "
1;
b10010 -
01
b11010 .
13
04
15
10
b10 #
b1110 *
b1101 ,
b1101 '
#475
0C
0H
0I
0;
b11 "
0D
11
03
b10011 -
1:
b11000 .
0<
14
05
1=
0@
00
19
b11 #
b1111 *
b1110 ,
b1110 '
#480
1C
1H
1I
1D
1<
0:
1@
b100 "
1;
b10100 -
01
b11110 .
13
04
15
10
b100 #
b110 )
b0 *
b1111 ,
b1111 '
#485
0!
0M
0E
0H
0D
0<
1:
0U
0;
b110 "
0V
03
1C
b110 -
0L
b0 .
0N
0?
05
0@
1F
0G
0I
0O
0R
0/
18
00
09
0B
0K
b110 #
0$
b1 *
b110 +
b110 &
b0 ,
b0 '
#490
b111 "
b111 -
11
14
0!
10
b111 #
b10 *
b1 ,
b1 '
